[{"Id": "1499", "Title": "IoT for remote monitoring in Algeria", "Author": "KHABABA  Abdallah", "Grade": "Professeur", "Taken": true, "Priority 1": "F3I", "Priority 2": "IDTW", "Priority 3": "IFIA", "Priority 4": "GL", "Priority 5": "RSD", "Date": "2022-01-04", "Time": "09:49:23"}, {"Id": "1501", "Title": "Development, Usability, and Efficiancy of a Serious Game in aiding to regain cognitive functions.", "Author": "KHABABA  Abdallah", "Grade": "Professeur", "Taken": true, "Priority 1": "GL", "Priority 2": "IFIA", "Priority 3": "F3I", "Priority 4": "IDTW", "Priority 5": "RSD", "Date": "2022-01-02", "Time": "19:21:14"}, {"Id": "1502", "Title": "Conception et R\u00e9alisation d\u2019un syst\u00e8me de r\u00e9alit\u00e9 augment\u00e9e appliqu\u00e9e aux op\u00e9rations sur les syst\u00e8mes Industriels. (Ing\u00e9nierie et outils num\u00e9riques)", "Author": "KHABABA  Abdallah", "Grade": "Professeur", "Taken": true, "Priority 1": "F3I", "Priority 2": "RSD", "Priority 3": "IDTW", "Priority 4": "GL", "Priority 5": "IFIA", "Date": "2022-01-16", "Time": "12:13:05"}, {"Id": "1504", "Title": "An IoT Based Mobile Augmented Reality Application for Energy Visualization", "Author": "KHABABA  Abdallah", "Grade": "Professeur", "Taken": true, "Priority 1": "F3I", "Priority 2": "IDTW", "Priority 3": "GL", "Priority 4": "IFIA", "Priority 5": "RSD", "Date": "2022-01-04", "Time": "09:50:25"}, {"Id": "1363", "Title": "Architecture d\u2019un Syst\u00e8me Nano Macro de R\u00e9seaux de Capteurs sans Fil connect\u00e9 \u00e0 IoT  pour une Agriculture Moderne", "Author": "ALIOUAT  Makhlouf", "Grade": "Professeur", "Taken": true, "Priority 1": "RSD", "Priority 2": "IDTW", "Priority 3": "IFIA", "Priority 4": "GL", "Priority 5": "F3I", "Date": "2022-01-02", "Time": "19:41:53"}, {"Id": "1364", "Title": "Distribution de Syst\u00e8mes  de Coordination des Feux de Circulation dans une Ville Intelligentes", "Author": "ALIOUAT  Makhlouf", "Grade": "Professeur", "Taken": true, "Priority 1": "RSD", "Priority 2": "IDTW", "Priority 3": "GL", "Priority 4": "IFIA", "Priority 5": "F3I", "Date": "2022-01-03", "Time": "19:48:18"}, {"Id": "1373", "Title": "sequential pattern mining", "Author": "KAMEL  Nadjet", "Grade": "Professeur", "Taken": true, "Priority 1": "IDTW", "Priority 2": "IFIA", "Priority 3": "RSD", "Priority 4": "F3I", "Priority 5": "GL", "Date": "2022-02-06", "Time": "09:32:43"}, {"Id": "1375", "Title": "Utility Pattern Mining", "Author": "KAMEL  Nadjet", "Grade": "Professeur", "Taken": false, "Priority 1": "IDTW", "Priority 2": "IFIA", "Priority 3": "RSD", "Priority 4": "F3I", "Priority 5": "GL", "Date": "2021-11-14", "Time": "11:34:21"}, {"Id": "1481", "Title": "Vision Transformer Based Deep Learning Models for Plant Disease Detection and Diagnosis", "Author": "MOUSSAOUI  Abdelouahab", "Grade": "Professeur", "Taken": true, "Priority 1": "F3I", "Priority 2": "IDTW", "Priority 3": "IFIA", "Priority 4": "GL", "Priority 5": "RSD", "Date": "2022-01-04", "Time": "09:43:24"}, {"Id": "1497", "Title": "Attention-Based Deep Convolutional Neural Network Versus Transfer Learning for Medical Image Classification and Disease Diagnosis", "Author": "MOUSSAOUI  Abdelouahab", "Grade": "Professeur", "Taken": true, "Priority 1": "F3I", "Priority 2": "IDTW", "Priority 3": "IFIA", "Priority 4": "GL", "Priority 5": "RSD", "Date": "2022-01-04", "Time": "09:47:46"}, {"Id": "1510", "Title": "Deep Feature Learning (Extraction and Generation) Using a Bidirectional LSTM-CNN and  Deep Generative Models (VAE, GAN) Applied to Physiological Signals (EEG/ECG) Classification", "Author": "MOUSSAOUI  Abdelouahab", "Grade": "Professeur", "Taken": true, "Priority 1": "F3I", "Priority 2": "IDTW", "Priority 3": "IFIA", "Priority 4": "GL", "Priority 5": "RSD", "Date": "2022-01-04", "Time": "09:51:34"}, {"Id": "1514", "Title": "Transformer-based Deep Learning Techniques for Speech Emotion Recognition and Sentiment Analysis", "Author": "MOUSSAOUI  Abdelouahab", "Grade": "Professeur", "Taken": true, "Priority 1": "F3I", "Priority 2": "IDTW", "Priority 3": "IFIA", "Priority 4": "GL", "Priority 5": "RSD", "Date": "2022-01-04", "Time": "09:53:01"}, {"Id": "1516", "Title": "Innovative Deep Neural Network Models for Multilingual Translation", "Author": "MOUSSAOUI  Abdelouahab", "Grade": "Professeur", "Taken": true, "Priority 1": "IDTW", "Priority 2": "F3I", "Priority 3": "IFIA", "Priority 4": "GL", "Priority 5": "RSD", "Date": "2022-01-05", "Time": "17:06:46"}, {"Id": "1517", "Title": "Community Detection with Deep Graph Neural Networks (GNN)", "Author": "MOUSSAOUI  Abdelouahab", "Grade": "Professeur", "Taken": true, "Priority 1": "IDTW", "Priority 2": "F3I", "Priority 3": "IFIA", "Priority 4": "GL", "Priority 5": "RSD", "Date": "2022-01-02", "Time": "19:48:41"}, {"Id": "1518", "Title": "Identification of Plant-Leaf Diseases Based Generative-Attention CNN and Transfer-Learning Approaches", "Author": "MOUSSAOUI  Abdelouahab", "Grade": "Professeur", "Taken": true, "Priority 1": "IDTW", "Priority 2": "F3I", "Priority 3": "IFIA", "Priority 4": "GL", "Priority 5": "RSD", "Date": "2022-01-05", "Time": "17:09:30"}, {"Id": "1519", "Title": "Deep Learning fo Medical Object Detection and Segmentation : Case of Osteoporosis Disease", "Author": "MOUSSAOUI  Abdelouahab", "Grade": "Professeur", "Taken": true, "Priority 1": "IDTW", "Priority 2": "F3I", "Priority 3": "IFIA", "Priority 4": "GL", "Priority 5": "RSD", "Date": "2022-01-05", "Time": "17:10:34"}, {"Id": "1520", "Title": "Classification of Remote Sensing Images using Transfer Learning and CNN Model with Attention", "Author": "MOUSSAOUI  Abdelouahab", "Grade": "Professeur", "Taken": true, "Priority 1": "F3I", "Priority 2": "IDTW", "Priority 3": "IFIA", "Priority 4": "GL", "Priority 5": "RSD", "Date": "2022-01-04", "Time": "09:54:57"}, {"Id": "1538", "Title": "Very Deep Attention-Based Models for Sentiments Analysis and Text Classification", "Author": "MOUSSAOUI  Abdelouahab", "Grade": "Professeur", "Taken": true, "Priority 1": "IDTW", "Priority 2": "F3I", "Priority 3": "IFIA", "Priority 4": "GL", "Priority 5": "RSD", "Date": "2022-01-05", "Time": "17:19:07"}, {"Id": "1672", "Title": "Novel Deep Learning Architecture for Predicting Heart Diseases based Transformers and Attention Mechanism with Explainability Model", "Author": "MOUSSAOUI  Abdelouahab", "Grade": "Professeur", "Taken": true, "Priority 1": "GL", "Priority 2": "IDTW", "Priority 3": "IFIA", "Priority 4": "F3I", "Priority 5": "RSD", "Date": "2022-01-22", "Time": "12:54:51"}, {"Id": "1563", "Title": "Hate speech detection in tweets", "Author": "REFOUFI  Allaoua", "Grade": "Professeur", "Taken": true, "Priority 1": "IDTW", "Priority 2": "F3I", "Priority 3": "IFIA", "Priority 4": "GL", "Priority 5": "RSD", "Date": "2022-01-05", "Time": "17:43:24"}, {"Id": "1587", "Title": "Deep learning based sentiment analysis of movie reviews", "Author": "REFOUFI  Allaoua", "Grade": "Professeur", "Taken": true, "Priority 1": "IDTW", "Priority 2": "IFIA", "Priority 3": "GL", "Priority 4": "RSD", "Priority 5": "", "Date": "2022-01-05", "Time": "17:52:46"}, {"Id": "1589", "Title": "\u00c9liminer les silos d\u2019information et unifier les syst\u00e8mes en les dotant de couches m\u00e9tiers", "Author": "SAIDI  Mohamed", "Grade": "Maitre de conferences classe A", "Taken": true, "Priority 1": "GL", "Priority 2": "IDTW", "Priority 3": "IFIA", "Priority 4": "RSD", "Priority 5": "F3I", "Date": "2022-01-02", "Time": "19:17:15"}, {"Id": "1590", "Title": "Fusion de syst\u00e8mes d'information", "Author": "SAIDI  Mohamed", "Grade": "Maitre de conferences classe A", "Taken": true, "Priority 1": "GL", "Priority 2": "IDTW", "Priority 3": "IFIA", "Priority 4": "RSD", "Priority 5": "F3I", "Date": "2022-01-02", "Time": "19:14:33"}, {"Id": "1453", "Title": "Protocole clustering les reseaux IoT bas\u00e9 deep learning", "Author": "ALIOUAT n\u00e9e ZOUAOUI  Zibouda", "Grade": "Professeur", "Taken": true, "Priority 1": "RSD", "Priority 2": "IDTW", "Priority 3": "IFIA", "Priority 4": "F3I", "Priority 5": "GL", "Date": "2022-01-17", "Time": "10:23:24"}, {"Id": "1454", "Title": "D\u00e9tection des cyber-attaques dans l\u2019internet des objets", "Author": "ALIOUAT n\u00e9e ZOUAOUI  Zibouda", "Grade": "Professeur", "Taken": true, "Priority 1": "RSD", "Priority 2": "IDTW", "Priority 3": "IFIA", "Priority 4": "F3I", "Priority 5": "GL", "Date": "2022-01-02", "Time": "19:44:45"}, {"Id": "1567", "Title": "Conception et R\u00e9alisation d'un MOOC orient\u00e9 R\u00e9seaux", "Author": "KHENTOUT  Chabane", "Grade": "Maitre de conferences classe B", "Taken": true, "Priority 1": "IDTW", "Priority 2": "IFIA", "Priority 3": "F3I", "Priority 4": "RSD", "Priority 5": "GL", "Date": "2022-01-05", "Time": "17:45:02"}, {"Id": "1462", "Title": "Syst\u00e8me d\u2019acquisition et de traitement des donn\u00e9es sur les accidents de la route en Alg\u00e9rie", "Author": "DOUIDI  Lamri", "Grade": "Maitre de conferences classe B", "Taken": true, "Priority 1": "IDTW", "Priority 2": "GL", "Priority 3": "RSD", "Priority 4": "IFIA", "Priority 5": "F3I", "Date": "2022-01-04", "Time": "20:19:41"}, {"Id": "1463", "Title": "Services web dans un environnement d\u2019apprentissage \u00e0 distance", "Author": "DOUIDI  Lamri", "Grade": "Maitre de conferences classe B", "Taken": true, "Priority 1": "IDTW", "Priority 2": "GL", "Priority 3": "RSD", "Priority 4": "IFIA", "Priority 5": "F3I", "Date": "2022-01-04", "Time": "20:22:03"}, {"Id": "1473", "Title": "Approche ontologique pour l\u2019indexation des ressources p\u00e9dagogiques num\u00e9riques", "Author": "DOUIDI  Lamri", "Grade": "Maitre de conferences classe B", "Taken": true, "Priority 1": "GL", "Priority 2": "IDTW", "Priority 3": "IFIA", "Priority 4": "RSD", "Priority 5": "F3I", "Date": "2022-01-02", "Time": "19:16:15"}, {"Id": "1566", "Title": "Simulation de la propagation du Covid19 (CoronaVirus) par les Syst\u00e8mes Multi-Agents", "Author": "BENAOUDA  Abdelhafid", "Grade": "Maitre de conferences classe B", "Taken": true, "Priority 1": "RSD", "Priority 2": "IDTW", "Priority 3": "IFIA", "Priority 4": "F3I", "Priority 5": "GL", "Date": "2022-01-03", "Time": "18:48:41"}, {"Id": "1568", "Title": "Un mod\u00e8le bas\u00e9 \"resource LoadBalancing\"  dans les Infrastructures as a Services (IaaS) des Cloud-Computing.", "Author": "BENAOUDA  Abdelhafid", "Grade": "Maitre de conferences classe B", "Taken": true, "Priority 1": "RSD", "Priority 2": "IDTW", "Priority 3": "IFIA", "Priority 4": "F3I", "Priority 5": "GL", "Date": "2022-01-03", "Time": "18:32:43"}, {"Id": "1576", "Title": "Simulation  d'un syst\u00e8me automatis\u00e9  mod\u00e9lis\u00e9  par grafcets  hi\u00e9rarchiques (Encadr\u00e9 par Dr. Nac\u00e9ra Benaouda)", "Author": "BENAOUDA  Abdelhafid", "Grade": "Maitre de conferences classe B", "Taken": false, "Priority 1": "GL", "Priority 2": "IFIA", "Priority 3": "RSD", "Priority 4": "IDTW", "Priority 5": "F3I", "Date": "2021-11-20", "Time": "18:25:10"}, {"Id": "1534", "Title": "Redressement des notes obtenues par diff\u00e9rentes formes d\u2019\u00e9valuation", "Author": "KHENTOUT n\u00e9e HARBOUCHE  Khadidja", "Grade": "Maitre de conferences classe B", "Taken": true, "Priority 1": "IFIA", "Priority 2": "IDTW", "Priority 3": "F3I", "Priority 4": "RSD", "Priority 5": "GL", "Date": "2022-01-04", "Time": "18:31:54"}, {"Id": "1539", "Title": "Mesure de similarit\u00e9 et classification des profils comportementaux des apprenants fond\u00e9es sur des r\u00e9seaux de neurones", "Author": "KHENTOUT n\u00e9e HARBOUCHE  Khadidja", "Grade": "Maitre de conferences classe B", "Taken": true, "Priority 1": "IDTW", "Priority 2": "IFIA", "Priority 3": "F3I", "Priority 4": "RSD", "Priority 5": "GL", "Date": "2022-01-09", "Time": "11:24:25"}, {"Id": "1490", "Title": "Content based Recommender System using Deep Learning", "Author": "ZAIMEN n\u00e9e MEDIANI  Chahrazed", "Grade": "Maitre de conferences classe B", "Taken": true, "Priority 1": "IDTW", "Priority 2": "F3I", "Priority 3": "IFIA", "Priority 4": "RSD", "Priority 5": "GL", "Date": "2022-01-05", "Time": "17:02:38"}, {"Id": "1491", "Title": "Collaborative Recommender System using Deep Learning", "Author": "ZAIMEN n\u00e9e MEDIANI  Chahrazed", "Grade": "Maitre de conferences classe B", "Taken": true, "Priority 1": "IDTW", "Priority 2": "F3I", "Priority 3": "IFIA", "Priority 4": "RSD", "Priority 5": "GL", "Date": "2022-01-05", "Time": "17:04:13"}, {"Id": "1558", "Title": "A Hybrid recommendation algorithm for learning resources", "Author": "ZAIMEN n\u00e9e MEDIANI  Chahrazed", "Grade": "Maitre de conferences classe B", "Taken": true, "Priority 1": "F3I", "Priority 2": "IDTW", "Priority 3": "IFIA", "Priority 4": "RSD", "Priority 5": "GL", "Date": "2022-01-04", "Time": "09:59:35"}, {"Id": "1569", "Title": "Resources Allocation and scheduling problems", "Author": "MECHTA  Djamila", "Grade": "Maitre de conferences classe A", "Taken": true, "Priority 1": "RSD", "Priority 2": "IFIA", "Priority 3": "IDTW", "Priority 4": "F3I", "Priority 5": "GL", "Date": "2022-01-03", "Time": "18:25:47"}, {"Id": "1570", "Title": "Artificial Intelligence-powered edge computing", "Author": "MECHTA  Djamila", "Grade": "Maitre de conferences classe A", "Taken": true, "Priority 1": "RSD", "Priority 2": "IFIA", "Priority 3": "IDTW", "Priority 4": "F3I", "Priority 5": "GL", "Date": "2022-01-03", "Time": "18:28:01"}, {"Id": "1571", "Title": "Security in critical IoMT and IIoT", "Author": "MECHTA  Djamila", "Grade": "Maitre de conferences classe A", "Taken": true, "Priority 1": "RSD", "Priority 2": "IFIA", "Priority 3": "IDTW", "Priority 4": "F3I", "Priority 5": "GL", "Date": "2022-01-02", "Time": "19:42:48"}, {"Id": "1572", "Title": "Bio-inspired based Power routing in P2P energy trading systems", "Author": "MECHTA  Djamila", "Grade": "Maitre de conferences classe A", "Taken": true, "Priority 1": "IFIA", "Priority 2": "RSD", "Priority 3": "IDTW", "Priority 4": "F3I", "Priority 5": "GL", "Date": "2022-01-04", "Time": "18:47:29"}, {"Id": "1381", "Title": "Formalisation des Protocoles d'Interaction dans les SMA", "Author": "LAOUADI  Mohamed Amin", "Grade": "Maitre de conferences classe B", "Taken": true, "Priority 1": "IFIA", "Priority 2": "IDTW", "Priority 3": "RSD", "Priority 4": "F3I", "Priority 5": "GL", "Date": "2022-01-04", "Time": "17:55:46"}, {"Id": "1428", "Title": "V\u00e9rification des protocoles d\u2019interaction dans les SMA", "Author": "LAOUADI  Mohamed Amin", "Grade": "Maitre de conferences classe B", "Taken": true, "Priority 1": "IFIA", "Priority 2": "IDTW", "Priority 3": "RSD", "Priority 4": "F3I", "Priority 5": "GL", "Date": "2022-01-09", "Time": "13:17:04"}, {"Id": "1544", "Title": "Un nouveau paradigme de s\u00e9curit\u00e9 pour les r\u00e9seaux de drones utilisant un syst\u00e8me immunitaire artificiel", "Author": "BEGHRICHE  Abdesselem", "Grade": "Maitre de conferences classe B", "Taken": true, "Priority 1": "RSD", "Priority 2": "IFIA", "Priority 3": "IDTW", "Priority 4": "GL", "Priority 5": "F3I", "Date": "2022-01-03", "Time": "20:03:21"}, {"Id": "1545", "Title": "un routage efficace pour les r\u00e9seaux de drones bas\u00e9 sur le comprtement des peinguins.", "Author": "BEGHRICHE  Abdesselem", "Grade": "Maitre de conferences classe B", "Taken": true, "Priority 1": "RSD", "Priority 2": "IFIA", "Priority 3": "IDTW", "Priority 4": "F3I", "Priority 5": "GL", "Date": "2022-01-10", "Time": "11:37:46"}, {"Id": "1542", "Title": "Secure Clock Synchronization in Wireless Sensor Networks", "Author": "AISSAOUA  Habib", "Grade": "Maitre de conferences classe B", "Taken": true, "Priority 1": "RSD", "Priority 2": "IFIA", "Priority 3": "IDTW", "Priority 4": "F3I", "Priority 5": "GL", "Date": "2022-01-03", "Time": "20:08:47"}, {"Id": "1559", "Title": "Clock synchronization in WSNs", "Author": "AISSAOUA  Habib", "Grade": "Maitre de conferences classe B", "Taken": false, "Priority 1": "RSD", "Priority 2": "IFIA", "Priority 3": "IDTW", "Priority 4": "F3I", "Priority 5": "GL", "Date": "2021-11-20", "Time": "12:34:32"}, {"Id": "1578", "Title": "protocole optimal pour la localisation des n\u0153uds dans les VANETs", "Author": "BENAIDJA  Amira", "Grade": "Maitre de conferences classe B", "Taken": true, "Priority 1": "RSD", "Priority 2": "IFIA", "Priority 3": "IDTW", "Priority 4": "GL", "Priority 5": "F3I", "Date": "2022-01-03", "Time": "20:30:22"}, {"Id": "1582", "Title": "An access method for the broadcast of safety messages in IEEE 802.11p VANETs", "Author": "BENAIDJA  Amira", "Grade": "Maitre de conferences classe B", "Taken": true, "Priority 1": "RSD", "Priority 2": "IFIA", "Priority 3": "IDTW", "Priority 4": "GL", "Priority 5": "F3I", "Date": "2022-01-15", "Time": "16:27:19"}, {"Id": "1535", "Title": "Approche pour l'extraction des caract\u00e9ristiques et la d\u00e9couverte des connaissances dans les images d'expression g\u00e9n\u00e9tique", "Author": "MEKROUD  Noureddine", "Grade": "Maitre assistant classe A", "Taken": true, "Priority 1": "F3I", "Priority 2": "IFIA", "Priority 3": "IDTW", "Priority 4": "GL", "Priority 5": "RSD", "Date": "2022-01-04", "Time": "09:57:24"}, {"Id": "1536", "Title": "Extraction des r\u00e8gles d'association en logique \u00e9videntielle, mod\u00e9lisation des distances ad\u00e9quates aux donn\u00e9es d'expression g\u00e9n\u00e9tique", "Author": "MEKROUD  Noureddine", "Grade": "Maitre assistant classe A", "Taken": true, "Priority 1": "IFIA", "Priority 2": "F3I", "Priority 3": "IDTW", "Priority 4": "GL", "Priority 5": "RSD", "Date": "2022-01-04", "Time": "18:33:05"}, {"Id": "1537", "Title": "Extraction des motifs s\u00e9quentiels flous et possibilistes \u00e0 partir des donn\u00e9es d'expression g\u00e9n\u00e9tique.", "Author": "MEKROUD  Noureddine", "Grade": "Maitre assistant classe A", "Taken": true, "Priority 1": "IFIA", "Priority 2": "F3I", "Priority 3": "IDTW", "Priority 4": "GL", "Priority 5": "RSD", "Date": "2022-01-04", "Time": "18:34:11"}, {"Id": "1443", "Title": "Impl\u00e9mentation d'un nouveau sch\u00e9ma  de cryptographie en boite blanche", "Author": "KHARCHI  Samia", "Grade": "Maitre assistant classe A", "Taken": true, "Priority 1": "RSD", "Priority 2": "IDTW", "Priority 3": "IFIA", "Priority 4": "GL", "Priority 5": "F3I", "Date": "2022-01-03", "Time": "20:06:17"}, {"Id": "1500", "Title": "Les codes QR: S\u00e9curit\u00e9 et authentification", "Author": "KHARCHI  Samia", "Grade": "Maitre assistant classe A", "Taken": true, "Priority 1": "RSD", "Priority 2": "IDTW", "Priority 3": "IFIA", "Priority 4": "GL", "Priority 5": "F3I", "Date": "2022-01-02", "Time": "19:43:44"}, {"Id": "1592", "Title": "SDVN : Software Defined Vehicular Networks", "Author": "HAMMOUCHE  Yassine", "Grade": "Maitre assistant classe A", "Taken": true, "Priority 1": "RSD", "Priority 2": "GL", "Priority 3": "IFIA", "Priority 4": "IDTW", "Priority 5": "F3I", "Date": "2022-01-03", "Time": "19:51:58"}, {"Id": "1593", "Title": "Un nouveau protocole de routage Cross-layer pour Vanets.", "Author": "HAMMOUCHE  Yassine", "Grade": "Maitre assistant classe A", "Taken": true, "Priority 1": "RSD", "Priority 2": "IFIA", "Priority 3": "F3I", "Priority 4": "IDTW", "Priority 5": "GL", "Date": "2022-01-03", "Time": "20:02:31"}, {"Id": "1560", "Title": "D\u00e9veloppement de l\u2019intelligence artificielle dans le domaine de l\u2019Internet des Objets", "Author": "FENANIR  Samir", "Grade": "Maitre de conferences classe B", "Taken": true, "Priority 1": "IFIA", "Priority 2": "F3I", "Priority 3": "RSD", "Priority 4": "GL", "Priority 5": "IDTW", "Date": "2022-01-04", "Time": "18:39:41"}, {"Id": "1561", "Title": "Syst\u00e8me de d\u00e9tection des intrusions pour l\u2019internet des objets en utilisant des techniques d\u2019apprentissage automatique", "Author": "FENANIR  Samir", "Grade": "Maitre de conferences classe B", "Taken": true, "Priority 1": "IFIA", "Priority 2": "RSD", "Priority 3": "F3I", "Priority 4": "GL", "Priority 5": "IDTW", "Date": "2022-01-04", "Time": "18:40:57"}, {"Id": "1562", "Title": "Syst\u00e8me de d\u00e9tection des intrusions pour l\u2019internet des objets en utilisant des techniques d\u2019apprentissage approfondi", "Author": "FENANIR  Samir", "Grade": "Maitre de conferences classe B", "Taken": true, "Priority 1": "IFIA", "Priority 2": "RSD", "Priority 3": "F3I", "Priority 4": "GL", "Priority 5": "IDTW", "Date": "2022-01-03", "Time": "20:12:30"}, {"Id": "1579", "Title": "Reconnaissance des \u00e9motions implicites", "Author": "LAKHFIF  Abdelaziz", "Grade": "Maitre de conferences classe A", "Taken": true, "Priority 1": "IDTW", "Priority 2": "IFIA", "Priority 3": "F3I", "Priority 4": "GL", "Priority 5": "RSD", "Date": "2022-01-05", "Time": "17:47:08"}, {"Id": "1580", "Title": "D\u00e9tection des \u00e9v\u00e8nements utiles dans Twitter", "Author": "LAKHFIF  Abdelaziz", "Grade": "Maitre de conferences classe A", "Taken": true, "Priority 1": "IDTW", "Priority 2": "IFIA", "Priority 3": "F3I", "Priority 4": "GL", "Priority 5": "RSD", "Date": "2022-01-05", "Time": "17:48:25"}, {"Id": "1581", "Title": "G\u00e9n\u00e9ration des sc\u00e8nes 3D \u00e0 partir des graphes s\u00e9mantiques", "Author": "LAKHFIF  Abdelaziz", "Grade": "Maitre de conferences classe A", "Taken": true, "Priority 1": "IFIA", "Priority 2": "IDTW", "Priority 3": "F3I", "Priority 4": "GL", "Priority 5": "RSD", "Date": "2022-01-04", "Time": "18:48:40"}, {"Id": "1511", "Title": "Newsql databases administration and tuning", "Author": "TOUMI  Lyazid", "Grade": "Maitre de conferences classe A", "Taken": true, "Priority 1": "IDTW", "Priority 2": "GL", "Priority 3": "F3I", "Priority 4": "RSD", "Priority 5": "IFIA", "Date": "2022-01-04", "Time": "09:52:30"}, {"Id": "1550", "Title": "NoSQL Databases for Geospatial Queries: Study and Scalability benchmarking", "Author": "TOUMI  Lyazid", "Grade": "Maitre de conferences classe A", "Taken": true, "Priority 1": "IDTW", "Priority 2": "GL", "Priority 3": "F3I", "Priority 4": "RSD", "Priority 5": "IFIA", "Date": "2022-01-05", "Time": "17:38:47"}, {"Id": "1551", "Title": "Covid-19 pandemic: how to analyze human sentiments?", "Author": "TOUMI  Lyazid", "Grade": "Maitre de conferences classe A", "Taken": true, "Priority 1": "IDTW", "Priority 2": "F3I", "Priority 3": "IFIA", "Priority 4": "GL", "Priority 5": "RSD", "Date": "2022-01-04", "Time": "17:43:26"}, {"Id": "1585", "Title": "Intelligent Assistant Seller with Sign Language", "Author": "TOUMI  Lyazid", "Grade": "Maitre de conferences classe A", "Taken": true, "Priority 1": "IDTW", "Priority 2": "F3I", "Priority 3": "GL", "Priority 4": "IFIA", "Priority 5": "RSD", "Date": "2022-01-05", "Time": "17:51:04"}, {"Id": "1359", "Title": "2)\tAPPLICATION DES META-HEURISTIQUES POUR L'OPTIMIZATION DE LA LOCALIZATION DANS LES RCSFS", "Author": "LALAMA  Zahia", "Grade": "Maitre assistant classe A", "Taken": true, "Priority 1": "RSD", "Priority 2": "IDTW", "Priority 3": "IFIA", "Priority 4": "GL", "Priority 5": "F3I", "Date": "2022-01-03", "Time": "18:40:54"}, {"Id": "1355", "Title": "Segmentation des images m\u00e9dicales en chol\u00e9cystectomie laparoscopique", "Author": "DJAGHLOUL  Haroun", "Grade": "Maitre assistant classe A", "Taken": true, "Priority 1": "F3I", "Priority 2": "IFIA", "Priority 3": "GL", "Priority 4": "IDTW", "Priority 5": "RSD", "Date": "2022-01-03", "Time": "20:57:14"}, {"Id": "1365", "Title": "\u062a\u0637\u0628\u064a\u0642 \u0627\u0644\u0648\u0627\u0642\u0639 \u0627\u0644\u0627\u0641\u062a\u0631\u0627\u0636\u064a \u0644\u0645\u0643\u0627\u0641\u062d\u0629 \u0648\u0628\u0627\u0621 \u0645\u0646 \u0646\u0648\u0639 \u0643\u0648\u0641\u064a\u062f 19 \u0641\u064a \u0648\u0633\u0637 \u062c\u0627\u0645\u0639\u064a", "Author": "DJAGHLOUL  Haroun", "Grade": "Maitre assistant classe A", "Taken": false, "Priority 1": "F3I", "Priority 2": "IFIA", "Priority 3": "GL", "Priority 4": "IDTW", "Priority 5": "RSD", "Date": "2021-11-12", "Time": "01:44:09"}, {"Id": "1484", "Title": "Deep learning pour l\u2019am\u00e9lioration du protocole IEEE802.11 DCF", "Author": "BANABIREZ n\u00e9e ZERGUINE  Nadia", "Grade": "Maitre de conferences classe B", "Taken": true, "Priority 1": "RSD", "Priority 2": "IFIA", "Priority 3": "IDTW", "Priority 4": "GL", "Priority 5": "F3I", "Date": "2022-01-03", "Time": "18:41:47"}, {"Id": "1485", "Title": "Am\u00e9lioration bas\u00e9 sur l\u2019apprentissage profond pour le support du flux temps r\u00e9el dans les MANETs", "Author": "BANABIREZ n\u00e9e ZERGUINE  Nadia", "Grade": "Maitre de conferences classe B", "Taken": true, "Priority 1": "RSD", "Priority 2": "IFIA", "Priority 3": "IDTW", "Priority 4": "GL", "Priority 5": "F3I", "Date": "2022-01-03", "Time": "18:45:49"}, {"Id": "1402", "Title": "Assessment explanation approaches for black box models", "Author": "DRIF  Ahlem", "Grade": "Maitre de conferences classe A", "Taken": true, "Priority 1": "IFIA", "Priority 2": "IDTW", "Priority 3": "F3I", "Priority 4": "RSD", "Priority 5": "GL", "Date": "2022-01-04", "Time": "17:58:52"}, {"Id": "1410", "Title": "A deep learning model for recommendation", "Author": "DRIF  Ahlem", "Grade": "Maitre de conferences classe A", "Taken": true, "Priority 1": "IFIA", "Priority 2": "F3I", "Priority 3": "IDTW", "Priority 4": "GL", "Priority 5": "RSD", "Date": "2022-01-04", "Time": "18:00:17"}, {"Id": "1419", "Title": "Etude et gestion des ph\u00e9nom\u00e8nes d\u2019attente.", "Author": "AMRANI  Lakhdar", "Grade": "Maitre assistant classe A", "Taken": true, "Priority 1": "IFIA", "Priority 2": "GL", "Priority 3": "F3I", "Priority 4": "IDTW", "Priority 5": "RSD", "Date": "2022-01-06", "Time": "08:34:17"}, {"Id": "1420", "Title": "Analyse post-optimale en programmation lin\u00e9aire.", "Author": "AMRANI  Lakhdar", "Grade": "Maitre assistant classe A", "Taken": false, "Priority 1": "IFIA", "Priority 2": "GL", "Priority 3": "IDTW", "Priority 4": "F3I", "Priority 5": "RSD", "Date": "2021-11-17", "Time": "15:45:05"}, {"Id": "1541", "Title": "Assistance \u00e0 la sp\u00e9cification de propri\u00e9t\u00e9s temporelles", "Author": "BOUAMARI  Abdelkader", "Grade": "Maitre assistant classe A", "Taken": true, "Priority 1": "IDTW", "Priority 2": "IFIA", "Priority 3": "RSD", "Priority 4": "GL", "Priority 5": "F3I", "Date": "2022-01-05", "Time": "17:20:23"}, {"Id": "1543", "Title": "Model-checking via le web", "Author": "BOUAMARI  Abdelkader", "Grade": "Maitre assistant classe A", "Taken": true, "Priority 1": "IDTW", "Priority 2": "RSD", "Priority 3": "GL", "Priority 4": "IFIA", "Priority 5": "F3I", "Date": "2022-01-05", "Time": "17:21:25"}, {"Id": "1492", "Title": "comparaison d\u2019algorithmes d\u2019optimisation quantiques: les m\u00e9taheuristiques quantiques QPSO et  QGA", "Author": "ZAZOUA n\u00e9e DJEMAME  Safia", "Grade": "Maitre de conferences classe B", "Taken": true, "Priority 1": "IFIA", "Priority 2": "F3I", "Priority 3": "IDTW", "Priority 4": "GL", "Priority 5": "RSD", "Date": "2022-01-04", "Time": "18:08:53"}, {"Id": "1493", "Title": "Am\u00e9lioration d'images avec le Deep Learning", "Author": "ZAZOUA n\u00e9e DJEMAME  Safia", "Grade": "Maitre de conferences classe B", "Taken": true, "Priority 1": "F3I", "Priority 2": "IFIA", "Priority 3": "IDTW", "Priority 4": "GL", "Priority 5": "RSD", "Date": "2022-01-04", "Time": "09:46:23"}, {"Id": "1556", "Title": "Modelisation 3D d'un environnement virtuel", "Author": "DOUAR  Amel", "Grade": "Maitre assistant classe A", "Taken": true, "Priority 1": "IDTW", "Priority 2": "F3I", "Priority 3": "IFIA", "Priority 4": "GL", "Priority 5": "RSD", "Date": "2022-01-05", "Time": "17:41:53"}, {"Id": "1557", "Title": "extraction des informations pertinantes dans un texte", "Author": "DOUAR  Amel", "Grade": "Maitre assistant classe A", "Taken": true, "Priority 1": "IFIA", "Priority 2": "IDTW", "Priority 3": "GL", "Priority 4": "F3I", "Priority 5": "RSD", "Date": "2022-01-04", "Time": "18:38:11"}, {"Id": "1415", "Title": "An enhanced receiver-initiated MAC protocol for wireless sensor networks", "Author": "GOUDJIL  Lakhdar", "Grade": "Maitre assistant classe A", "Taken": true, "Priority 1": "RSD", "Priority 2": "IDTW", "Priority 3": "IFIA", "Priority 4": "F3I", "Priority 5": "GL", "Date": "2022-01-03", "Time": "18:47:58"}, {"Id": "1416", "Title": "A Receiver-Initiated Asynchronous Duty-Cycle MAC Protocol  for the Internet of Things", "Author": "GOUDJIL  Lakhdar", "Grade": "Maitre assistant classe A", "Taken": true, "Priority 1": "RSD", "Priority 2": "IDTW", "Priority 3": "IFIA", "Priority 4": "F3I", "Priority 5": "GL", "Date": "2022-01-03", "Time": "20:04:18"}, {"Id": "1407", "Title": "S\u00e9curisation des images m\u00e9dicales", "Author": "KHALFALLAH n\u00e9e HADI  Fairouz", "Grade": "Maitre de conferences classe B", "Taken": true, "Priority 1": "F3I", "Priority 2": "RSD", "Priority 3": "IDTW", "Priority 4": "GL", "Priority 5": "IFIA", "Date": "2022-01-04", "Time": "09:26:05"}, {"Id": "1408", "Title": "L\u2019apprentissage profond (Deep Learning) pour la classification automatique d\u2019images par le contenu visuel", "Author": "KHALFALLAH n\u00e9e HADI  Fairouz", "Grade": "Maitre de conferences classe B", "Taken": true, "Priority 1": "F3I", "Priority 2": "IFIA", "Priority 3": "RSD", "Priority 4": "GL", "Priority 5": "IDTW", "Date": "2022-01-04", "Time": "09:27:19"}, {"Id": "1409", "Title": "Content Based Image Retrieval on Cloud Computing", "Author": "KHALFALLAH n\u00e9e HADI  Fairouz", "Grade": "Maitre de conferences classe B", "Taken": true, "Priority 1": "F3I", "Priority 2": "RSD", "Priority 3": "IFIA", "Priority 4": "IDTW", "Priority 5": "GL", "Date": "2022-01-04", "Time": "09:29:23"}, {"Id": "1356", "Title": "Un nouvel algorithme auto-stabilisant pour le calcul d\u2019un ensemble dominant fort (Strong Dominating Set)", "Author": "GUELLATI  Nabil", "Grade": "Maitre de conferences classe B", "Taken": true, "Priority 1": "RSD", "Priority 2": "GL", "Priority 3": "IFIA", "Priority 4": "IDTW", "Priority 5": "F3I", "Date": "2022-01-03", "Time": "20:18:59"}, {"Id": "1449", "Title": "A Modified Black Widow Optimization algorithm for multilevel thresholding image segmentation", "Author": "SEMCHEDINE  Moussa", "Grade": "Maitre de conferences classe B", "Taken": true, "Priority 1": "F3I", "Priority 2": "IFIA", "Priority 3": "IDTW", "Priority 4": "RSD", "Priority 5": "GL", "Date": "2022-01-04", "Time": "09:33:37"}, {"Id": "1456", "Title": "Tuning deep learning parameters using bio-inspired algorithm", "Author": "SEMCHEDINE  Moussa", "Grade": "Maitre de conferences classe B", "Taken": true, "Priority 1": "IDTW", "Priority 2": "IFIA", "Priority 3": "F3I", "Priority 4": "RSD", "Priority 5": "GL", "Date": "2022-01-04", "Time": "20:18:36"}, {"Id": "1528", "Title": "Modeling of gene regulatory networks: graphycal aproache", "Author": "BRAHIM-SALEM  Fatiha", "Grade": "Maitre assistant classe A", "Taken": true, "Priority 1": "IDTW", "Priority 2": "F3I", "Priority 3": "IFIA", "Priority 4": "GL", "Priority 5": "RSD", "Date": "2022-01-05", "Time": "17:15:13"}, {"Id": "1530", "Title": "Modeling of gene regulatory networks: Bayesian Networks", "Author": "BRAHIM-SALEM  Fatiha", "Grade": "Maitre assistant classe A", "Taken": true, "Priority 1": "IDTW", "Priority 2": "F3I", "Priority 3": "IFIA", "Priority 4": "GL", "Priority 5": "RSD", "Date": "2022-01-05", "Time": "17:16:53"}, {"Id": "1527", "Title": "Megatron project, the hardware part", "Author": "KARA  Abdelaziz", "Grade": "Maitre assistant classe A", "Taken": false, "Priority 1": "RSD", "Priority 2": "F3I", "Priority 3": "IDTW", "Priority 4": "IFIA", "Priority 5": "GL", "Date": "2021-11-19", "Time": "06:20:15"}, {"Id": "1529", "Title": "Megatron project, the software part", "Author": "KARA  Abdelaziz", "Grade": "Maitre assistant classe A", "Taken": false, "Priority 1": "RSD", "Priority 2": "F3I", "Priority 3": "IDTW", "Priority 4": "IFIA", "Priority 5": "GL", "Date": "2021-11-19", "Time": "06:21:49"}, {"Id": "1575", "Title": "Security and Privacy in Internet of Things : RPL Protool", "Author": "MANSOURI  Houceme", "Grade": "Maitre de conferences classe A", "Taken": true, "Priority 1": "RSD", "Priority 2": "IDTW", "Priority 3": "IFIA", "Priority 4": "F3I", "Priority 5": "GL", "Date": "2022-02-08", "Time": "14:52:49"}, {"Id": "1577", "Title": "Security and Privacy in Internet of Things : LOADng Protocol", "Author": "MANSOURI  Houceme", "Grade": "Maitre de conferences classe A", "Taken": true, "Priority 1": "RSD", "Priority 2": "IDTW", "Priority 3": "IFIA", "Priority 4": "F3I", "Priority 5": "GL", "Date": "2022-02-08", "Time": "14:51:48"}, {"Id": "1406", "Title": "Heart Failure Prediction Using Machine Learning Techniques", "Author": "NASRI  Khaled", "Grade": "Maitre assistant classe B", "Taken": true, "Priority 1": "F3I", "Priority 2": "IDTW", "Priority 3": "IFIA", "Priority 4": "GL", "Priority 5": "RSD", "Date": "2022-01-04", "Time": "09:24:47"}, {"Id": "1429", "Title": "Deep Learning Model for Brain Tumor Radiogenomic Classification", "Author": "NASRI  Khaled", "Grade": "Maitre assistant classe B", "Taken": true, "Priority 1": "F3I", "Priority 2": "IFIA", "Priority 3": "GL", "Priority 4": "RSD", "Priority 5": "IDTW", "Date": "2022-01-04", "Time": "09:30:14"}, {"Id": "1387", "Title": "Arabic Sentiment Analysis using Deep Learning for algerian dialect", "Author": "TEBBANI  Fatiha", "Grade": "Maitre assistant classe A", "Taken": true, "Priority 1": "IFIA", "Priority 2": "IDTW", "Priority 3": "F3I", "Priority 4": "GL", "Priority 5": "RSD", "Date": "2022-01-04", "Time": "17:56:31"}, {"Id": "1388", "Title": "Sentiment analysis based Machine learning for Algerian dialect", "Author": "TEBBANI  Fatiha", "Grade": "Maitre assistant classe A", "Taken": true, "Priority 1": "IFIA", "Priority 2": "F3I", "Priority 3": "IDTW", "Priority 4": "GL", "Priority 5": "RSD", "Date": "2022-01-11", "Time": "17:17:49"}, {"Id": "1423", "Title": "Routing Over Low power and Lossy networks.", "Author": "KANOUNI  Lakhdar", "Grade": "Maitre assistant classe B", "Taken": false, "Priority 1": "RSD", "Priority 2": "IFIA", "Priority 3": "IDTW", "Priority 4": "GL", "Priority 5": "F3I", "Date": "2021-11-17", "Time": "17:48:22"}, {"Id": "1425", "Title": "Le routage dans les r\u00e9seaux LLNs.", "Author": "KANOUNI  Lakhdar", "Grade": "Maitre assistant classe B", "Taken": true, "Priority 1": "RSD", "Priority 2": "IFIA", "Priority 3": "F3I", "Priority 4": "GL", "Priority 5": "IDTW", "Date": "2022-01-03", "Time": "18:32:00"}, {"Id": "1433", "Title": "Probl\u00e8me de d\u00e9tection/couverture des fronti\u00e8res dans les RCFs", "Author": "LAMRAOUI  Amar", "Grade": "Maitre assistant classe A", "Taken": true, "Priority 1": "RSD", "Priority 2": "IDTW", "Priority 3": "IFIA", "Priority 4": "F3I", "Priority 5": "", "Date": "2022-01-03", "Time": "20:14:01"}, {"Id": "1471", "Title": "Impl\u00e9mentation d\u2019un syst\u00e8me de cordonn\u00e9es virtuelles pour le routage dans les r\u00e9seaux de capteurs sans fil.", "Author": "LAMRAOUI  Amar", "Grade": "Maitre assistant classe A", "Taken": true, "Priority 1": "RSD", "Priority 2": "IDTW", "Priority 3": "IFIA", "Priority 4": "F3I", "Priority 5": "", "Date": "2022-01-03", "Time": "19:54:15"}, {"Id": "1619", "Title": "Implementation of a real IoT system", "Author": "LOUAIL  Lemia", "Grade": "Maitre de conferences classe A", "Taken": true, "Priority 1": "RSD", "Priority 2": "IFIA", "Priority 3": "IDTW", "Priority 4": "F3I", "Priority 5": "GL", "Date": "2022-01-03", "Time": "19:46:32"}, {"Id": "1421", "Title": "Task scheduling for IoT systems", "Author": "LOUAIL  Lemia", "Grade": "Maitre de conferences classe A", "Taken": true, "Priority 1": "RSD", "Priority 2": "IFIA", "Priority 3": "IDTW", "Priority 4": "GL", "Priority 5": "F3I", "Date": "2022-01-02", "Time": "19:28:20"}, {"Id": "1434", "Title": "Cross-layer routing for wireless sensor networks", "Author": "LOUAIL  Lemia", "Grade": "Maitre de conferences classe A", "Taken": true, "Priority 1": "RSD", "Priority 2": "IFIA", "Priority 3": "IDTW", "Priority 4": "GL", "Priority 5": "F3I", "Date": "2022-01-03", "Time": "18:26:49"}, {"Id": "1472", "Title": "Arabic offensive language detection in social media", "Author": "BESSOU  Sadik", "Grade": "Maitre de conferences classe A", "Taken": true, "Priority 1": "IDTW", "Priority 2": "F3I", "Priority 3": "IFIA", "Priority 4": "GL", "Priority 5": "RSD", "Date": "2022-01-05", "Time": "16:58:20"}, {"Id": "1474", "Title": "Arabic Subjective Sentiment Analysis Using Machine Learning", "Author": "BESSOU  Sadik", "Grade": "Maitre de conferences classe A", "Taken": true, "Priority 1": "IDTW", "Priority 2": "F3I", "Priority 3": "IFIA", "Priority 4": "GL", "Priority 5": "RSD", "Date": "2022-01-05", "Time": "16:59:20"}, {"Id": "1475", "Title": "Development of an Android Application for Anthroponymic Studies", "Author": "BESSOU  Sadik", "Grade": "Maitre de conferences classe A", "Taken": true, "Priority 1": "IDTW", "Priority 2": "F3I", "Priority 3": "IFIA", "Priority 4": "GL", "Priority 5": "RSD", "Date": "2022-01-05", "Time": "17:00:46"}, {"Id": "1457", "Title": "Study of generator-based mining frequent itemsets algorithms", "Author": "KARA Mohamed  Chafia", "Grade": "Maitre de conferences classe A", "Taken": true, "Priority 1": "F3I", "Priority 2": "IFIA", "Priority 3": "IDTW", "Priority 4": "RSD", "Priority 5": "GL", "Date": "2022-01-04", "Time": "09:34:22"}, {"Id": "1464", "Title": "Firefly-based feature selection for Arabic text classification", "Author": "KARA Mohamed  Chafia", "Grade": "Maitre de conferences classe A", "Taken": true, "Priority 1": "F3I", "Priority 2": "IFIA", "Priority 3": "IDTW", "Priority 4": "RSD", "Priority 5": "GL", "Date": "2022-01-04", "Time": "09:35:55"}, {"Id": "1455", "Title": "Adaptive flow-level scheduling for the IoT MAC in HWSN", "Author": "GHERBI  Chirihane", "Grade": "Maitre de conferences classe B", "Taken": true, "Priority 1": "RSD", "Priority 2": "IDTW", "Priority 3": "IFIA", "Priority 4": "F3I", "Priority 5": "GL", "Date": "2022-02-22", "Time": "00:54:46"}, {"Id": "1467", "Title": "M\u00e9canisme de contr\u00f4le de congestion dans  IoV", "Author": "GHERBI  Chirihane", "Grade": "Maitre de conferences classe B", "Taken": true, "Priority 1": "RSD", "Priority 2": "IFIA", "Priority 3": "IDTW", "Priority 4": "F3I", "Priority 5": "GL", "Date": "2022-01-02", "Time": "19:46:22"}, {"Id": "1553", "Title": "Protection de la vie priv\u00e9e dans le Cloud Computing", "Author": "KACHA  Lynda", "Grade": "Maitre assistant classe A", "Taken": true, "Priority 1": "IFIA", "Priority 2": "RSD", "Priority 3": "F3I", "Priority 4": "IDTW", "Priority 5": "GL", "Date": "2022-01-04", "Time": "18:35:14"}, {"Id": "1555", "Title": "Optimisation du processus d'anonymisation par les m\u00e9taheuristiques inspir\u00e9es de la nature", "Author": "KACHA  Lynda", "Grade": "Maitre assistant classe A", "Taken": true, "Priority 1": "IFIA", "Priority 2": "RSD", "Priority 3": "F3I", "Priority 4": "IDTW", "Priority 5": "GL", "Date": "2022-01-03", "Time": "20:29:17"}, {"Id": "1522", "Title": "Triggering Models: Measuring and Mitigating Bias in Arabic Language Generation", "Author": "Harrag  Fouzi", "Grade": "Maitre de conferences classe A", "Taken": true, "Priority 1": "IDTW", "Priority 2": "F3I", "Priority 3": "IFIA", "Priority 4": "GL", "Priority 5": "RSD", "Date": "2022-01-05", "Time": "17:11:47"}, {"Id": "1524", "Title": "Reducing toxicity in Arabic language generation models", "Author": "Harrag  Fouzi", "Grade": "Maitre de conferences classe A", "Taken": false, "Priority 1": "F3I", "Priority 2": "IDTW", "Priority 3": "IFIA", "Priority 4": "GL", "Priority 5": "RSD", "Date": "2022-02-06", "Time": "09:31:48"}, {"Id": "1525", "Title": "Using Multitask Unified Model (MUM) to improve search and NLU", "Author": "Harrag  Fouzi", "Grade": "Maitre de conferences classe A", "Taken": true, "Priority 1": "IDTW", "Priority 2": "F3I", "Priority 3": "IFIA", "Priority 4": "GL", "Priority 5": "RSD", "Date": "2022-01-05", "Time": "17:13:16"}, {"Id": "1460", "Title": "Towards a lightweight secure scheme for internet of things", "Author": "Cherbal  Sara", "Grade": "Maitre de conferences classe A", "Taken": true, "Priority 1": "RSD", "Priority 2": "IDTW", "Priority 3": "IFIA", "Priority 4": "F3I", "Priority 5": "GL", "Date": "2022-01-02", "Time": "19:27:28"}, {"Id": "1509", "Title": "Resource Management Approach in Fog Computing", "Author": "Cherbal  Sara", "Grade": "Maitre de conferences classe A", "Taken": true, "Priority 1": "RSD", "Priority 2": "IDTW", "Priority 3": "IFIA", "Priority 4": "F3I", "Priority 5": "GL", "Date": "2022-01-03", "Time": "18:25:11"}, {"Id": "1468", "Title": "Optimisation de la dur\u00e9e de vie dans les r\u00e9seaux de capteurs sans fil par le K-couverture", "Author": "BALBAL  Samir", "Grade": "Maitre de conferences classe B", "Taken": true, "Priority 1": "RSD", "Priority 2": "IFIA", "Priority 3": "IDTW", "Priority 4": "F3I", "Priority 5": "GL", "Date": "2022-01-02", "Time": "19:49:49"}, {"Id": "1469", "Title": "m\u00e9taheuritiques pour r\u00e9soudre le probl\u00e8me du sac \u00e0 dos multiple", "Author": "BALBAL  Samir", "Grade": "Maitre de conferences classe B", "Taken": true, "Priority 1": "IFIA", "Priority 2": "F3I", "Priority 3": "IDTW", "Priority 4": "GL", "Priority 5": "RSD", "Date": "2022-01-04", "Time": "18:06:50"}, {"Id": "1470", "Title": "Maximisation de la dur\u00e9e de vie des r\u00e9seaux de capteurs sans fil par les ensembles dominants", "Author": "BALBAL  Samir", "Grade": "Maitre de conferences classe B", "Taken": true, "Priority 1": "RSD", "Priority 2": "IFIA", "Priority 3": "F3I", "Priority 4": "IDTW", "Priority 5": "GL", "Date": "2022-01-10", "Time": "14:36:06"}, {"Id": "1398", "Title": "Etude comparative d'apprentissage approfondi pour la d\u00e9tection d'intrusion", "Author": "Frihia  hamza", "Grade": "Maitre de conferences classe B", "Taken": true, "Priority 1": "IFIA", "Priority 2": "F3I", "Priority 3": "IDTW", "Priority 4": "GL", "Priority 5": "RSD", "Date": "2022-01-04", "Time": "17:57:56"}, {"Id": "1476", "Title": "Smart groupware to support collaborative medical diagnosis", "Author": "Ferradji  mohamed", "Grade": "Maitre de conferences classe B", "Taken": true, "Priority 1": "IDTW", "Priority 2": "IFIA", "Priority 3": "F3I", "Priority 4": "RSD", "Priority 5": "GL", "Date": "2022-01-04", "Time": "09:42:32"}, {"Id": "1477", "Title": "Adaptive Network-based Fuzzy Inference Systems (ANFIS) optimization based on Particle Swarm Optimization (PSO)", "Author": "Ferradji  mohamed", "Grade": "Maitre de conferences classe B", "Taken": true, "Priority 1": "IFIA", "Priority 2": "IDTW", "Priority 3": "F3I", "Priority 4": "RSD", "Priority 5": "GL", "Date": "2022-01-04", "Time": "18:07:50"}, {"Id": "1436", "Title": "Filtrage des images m\u00e9dicales bas\u00e9 sur  l'EDP (EDP-based medical image filtering)", "Author": "BERRIMI  Fella", "Grade": "Maitre assistant classe A", "Taken": true, "Priority 1": "F3I", "Priority 2": "IFIA", "Priority 3": "GL", "Priority 4": "IDTW", "Priority 5": "RSD", "Date": "2022-01-04", "Time": "09:31:44"}, {"Id": "1448", "Title": "D\u00e9tection d'objets (pi\u00e9tons) bas\u00e9e sur HOG (HOG based object detection (pedestrians))", "Author": "BERRIMI  Fella", "Grade": "Maitre assistant classe A", "Taken": true, "Priority 1": "F3I", "Priority 2": "IFIA", "Priority 3": "GL", "Priority 4": "IDTW", "Priority 5": "RSD", "Date": "2022-01-03", "Time": "20:01:40"}, {"Id": "1552", "Title": "Path based approach for maximizing influence in signed social networks", "Author": "BOURAS  IKRAM", "Grade": "Maitre assistant classe B", "Taken": true, "Priority 1": "IFIA", "Priority 2": "RSD", "Priority 3": "GL", "Priority 4": "IDTW", "Priority 5": "F3I", "Date": "2022-01-10", "Time": "21:17:40"}, {"Id": "1554", "Title": "New variant of facility location problem in network design", "Author": "BOURAS  IKRAM", "Grade": "Maitre assistant classe B", "Taken": true, "Priority 1": "IFIA", "Priority 2": "RSD", "Priority 3": "GL", "Priority 4": "IDTW", "Priority 5": "F3I", "Date": "2022-01-04", "Time": "18:36:10"}, {"Id": "1489", "Title": "Approche bio-inspir\u00e9e pour un routage adaptatif dans les MANETs", "Author": "Kout  Akram", "Grade": "Maitre de conferences classe B) --> Hors d\u00e9partement: Facult\u00e9 de Biologie", "Taken": true, "Priority 1": "RSD", "Priority 2": "IFIA", "Priority 3": "GL", "Priority 4": "F3I", "Priority 5": "IDTW", "Date": "2022-02-07", "Time": "17:05:46"}, {"Id": "1496", "Title": "Solution Bio-inspir\u00e9e pour le routage dans les VANETs", "Author": "Kout  Akram", "Grade": "Maitre de conferences classe B) --> Hors d\u00e9partement: Facult\u00e9 de Biologie", "Taken": true, "Priority 1": "RSD", "Priority 2": "IFIA", "Priority 3": "GL", "Priority 4": "F3I", "Priority 5": "IDTW", "Date": "2022-01-03", "Time": "20:20:03"}, {"Id": "1526", "Title": "Planification automatique des cours en lignes bas\u00e9e sur les pr\u00e9f\u00e9rences des apprenants", "Author": "Kosrane  Mohamed", "Grade": "Maitre assistant classe A) --> Hors d\u00e9partement: Facult\u00e9 d'\u00e9conomie", "Taken": true, "Priority 1": "GL", "Priority 2": "IFIA", "Priority 3": "IDTW", "Priority 4": "F3I", "Priority 5": "RSD", "Date": "2022-01-02", "Time": "19:19:03"}, {"Id": "1482", "Title": "Estimation des pr\u00e9cipitations \u00e0 partir des images satellitaires en utilisant les r\u00e9seaux de neurones profonds", "Author": "Bouaita  Bilal", "Grade": "Maitre de conferences classe B) --> Hors d\u00e9partement: Facult\u00e9 de technologie", "Taken": true, "Priority 1": "F3I", "Priority 2": "GL", "Priority 3": "IFIA", "Priority 4": "IDTW", "Priority 5": "RSD", "Date": "2022-01-04", "Time": "09:45:07"}, {"Id": "1418", "Title": "Intelligent Optimization Approaches for the QoS-Driven Services Composition Problem in Dynamic IoT Environments", "Author": "SEGHIR  Fateh", "Grade": "Maitre de conferences classe B) --> Hors d\u00e9partement: Facult\u00e9 de technologie", "Taken": true, "Priority 1": "IFIA", "Priority 2": "IDTW", "Priority 3": "GL", "Priority 4": "F3I", "Priority 5": "RSD", "Date": "2022-01-04", "Time": "18:02:57"}, {"Id": "1458", "Title": "machine learning in forestry using remote sensing data", "Author": "CHERGUI  Nabila", "Grade": "Maitre de conferences classe B) --> Hors d\u00e9partement: Facult\u00e9 de technologie", "Taken": true, "Priority 1": "IFIA", "Priority 2": "F3I", "Priority 3": "IDTW", "Priority 4": "RSD", "Priority 5": "GL", "Date": "2022-01-04", "Time": "18:05:58"}, {"Id": "1357", "Title": "HTTP-Get DoS Attack Detection using Ontology", "Author": "Haddadi  Mohamed", "Grade": "Maitre de conferences classe B) --> Hors d\u00e9partement: Universit\u00e9 de Boumerdes, Departement \u00e9conomie", "Taken": true, "Priority 1": "IFIA", "Priority 2": "RSD", "Priority 3": "IDTW", "Priority 4": "F3I", "Priority 5": "GL", "Date": "2022-01-04", "Time": "17:53:06"}, {"Id": "1358", "Title": "HTTP flood DoS attack detection using data mining", "Author": "Haddadi  Mohamed", "Grade": "Maitre de conferences classe B) --> Hors d\u00e9partement: Universit\u00e9 de Boumerdes, Departement \u00e9conomie", "Taken": true, "Priority 1": "IDTW", "Priority 2": "IFIA", "Priority 3": "RSD", "Priority 4": "GL", "Priority 5": "F3I", "Date": "2022-01-21", "Time": "10:30:26"}, {"Id": "1430", "Title": "D\u00e9tecter les cyber-attaques en utilisant  data mining.techniques", "Author": "Haddadi  Mohamed", "Grade": "Maitre de conferences classe B) --> Hors d\u00e9partement: Universit\u00e9 de Boumerdes, Departement \u00e9conomie", "Taken": true, "Priority 1": "IDTW", "Priority 2": "IFIA", "Priority 3": "RSD", "Priority 4": "F3I", "Priority 5": "GL", "Date": "2022-01-16", "Time": "15:43:41"}, {"Id": "1369", "Title": "D\u00e9tection de la falsification des donn\u00e9es multim\u00e9dia", "Author": "Benmessahel  Bilel", "Grade": "Maitre de conferences classe B) --> Hors d\u00e9partement: Facult\u00e9 de technologie", "Taken": true, "Priority 1": "F3I", "Priority 2": "IFIA", "Priority 3": "IDTW", "Priority 4": "GL", "Priority 5": "RSD", "Date": "2022-01-04", "Time": "09:23:37"}, {"Id": "1380", "Title": "S\u00e9lection des caract\u00e9ristiques  pour les donn\u00e9es de grande dimension", "Author": "Benmessahel  Bilel", "Grade": "Maitre de conferences classe B) --> Hors d\u00e9partement: Facult\u00e9 de technologie", "Taken": false, "Priority 1": "IFIA", "Priority 2": "IDTW", "Priority 3": "F3I", "Priority 4": "RSD", "Priority 5": "GL", "Date": "2021-12-06", "Time": "08:32:14"}, {"Id": "1584", "Title": "D\u00e9veloppement d\u2019une application mobile sur le Cloud Computing pour la gestion de projet", "Author": "Annane  Boubakeur", "Grade": "Maitre assistant classe B", "Taken": true, "Priority 1": "GL", "Priority 2": "RSD", "Priority 3": "IFIA", "Priority 4": "IDTW", "Priority 5": "F3I", "Date": "2022-01-02", "Time": "19:13:29"}, {"Id": "1376", "Title": "Internet of Things Energy-Efficient routing protocol for eHealth systems", "Author": "Zier  Abdelhak", "Grade": "Maitre assistant classe B", "Taken": true, "Priority 1": "RSD", "Priority 2": "IFIA", "Priority 3": "IDTW", "Priority 4": "F3I", "Priority 5": "GL", "Date": "2022-01-03", "Time": "20:20:51"}, {"Id": "1483", "Title": "Authentification s\u00e9curis\u00e9e dans l\u2019internet des drones", "Author": "Harbi  Yasmine", "Grade": "Maitre assistant classe B", "Taken": true, "Priority 1": "RSD", "Priority 2": "IFIA", "Priority 3": "IDTW", "Priority 4": "F3I", "Priority 5": "GL", "Date": "2022-01-03", "Time": "18:37:04"}, {"Id": "1413", "Title": "Une approche de s\u00e9lection des caract\u00e9ristiques des compos\u00e9s dans les bases de donn\u00e9es chimiques \u00e0 la base d\u2019un algorithme PSO pour am\u00e9liorer les performances du processus du Criblage virtuel", "Author": "BERRHAIL  Fouaz", "Grade": "Maitre de conferences classe B) --> Hors d\u00e9partement: Faculte de technologie", "Taken": true, "Priority 1": "IFIA", "Priority 2": "IDTW", "Priority 3": "F3I", "Priority 4": "GL", "Priority 5": "", "Date": "2022-01-25", "Time": "12:49:59"}, {"Id": "1414", "Title": "R\u00e9alisation d\u2019un syst\u00e8me de d\u00e9tection des maladies v\u00e9g\u00e9tales au niveau des serres agricoles par l\u2019utilisation des techniques de l\u2019intelligence artificiel et le traitement d\u2019images", "Author": "BERRHAIL  Fouaz", "Grade": "Maitre de conferences classe B) --> Hors d\u00e9partement: Faculte de technologie", "Taken": true, "Priority 1": "IDTW", "Priority 2": "IFIA", "Priority 3": "F3I", "Priority 4": "GL", "Priority 5": "RSD", "Date": "2022-01-04", "Time": "20:17:34"}, {"Id": "1411", "Title": "Techniques de s\u00e9lection de fonctionnalit\u00e9s par l\u2019utilisation des algorithmes d'optimisation bio-inspir\u00e9s avec apprentissage automatique", "Author": "AYACHE  Farid", "Grade": "Maitre de conferences classe B) --> Hors d\u00e9partement: Faculte de technologie", "Taken": true, "Priority 1": "IFIA", "Priority 2": "F3I", "Priority 3": "GL", "Priority 4": "IDTW", "Priority 5": "RSD", "Date": "2022-01-04", "Time": "18:01:55"}]